treefuse/__init__.py
treefuse/treefuse.py
treefuse-1.1.2.dist-info/AUTHORS.rst
treefuse-1.1.2.dist-info/LICENSE
treefuse-1.1.2.dist-info/METADATA
treefuse-1.1.2.dist-info/WHEEL
treefuse-1.1.2.dist-info/top_level.txt
treefuse-1.1.2.dist-info/RECORD
