Metadata-Version: 2.1
Name: treefuse
Version: 1.1.2
Summary: TreeFuse creates a FUSE filesystem from a treelib.Tree
Home-page: https://github.com/OddBloke/treefuse
Author: Daniel Watkins
Author-email: daniel@daniel-watkins.co.uk
License: GNU General Public License v3
Keywords: treefuse
Platform: UNKNOWN
Classifier: Development Status :: 2 - Pre-Alpha
Classifier: Intended Audience :: Developers
Classifier: License :: OSI Approved :: GNU General Public License v3 (GPLv3)
Classifier: Natural Language :: English
Classifier: Programming Language :: Python :: 3
Classifier: Programming Language :: Python :: 3.7
Classifier: Programming Language :: Python :: 3.8
Requires-Python: >=3.7
Requires-Dist: fuse-python
Requires-Dist: treelib
